txv/__init__.py
txv/exp.py
txv/lrp_models.py
txv/lrp_modules.py
txv/models.py
txv/utils.py
txv/vit.py
txv/weights.py
txv-0.0.2.dist-info/LICENSE
txv-0.0.2.dist-info/METADATA
txv-0.0.2.dist-info/WHEEL
txv-0.0.2.dist-info/top_level.txt
txv-0.0.2.dist-info/RECORD
