Metadata-Version: 2.1
Name: txv
Version: 0.0.2
Summary: A Vision Transformer explainability package
Home-page: https://github.com/LokeshBadisa/txv
Author: Lokesh Badisa
Author-email: lokeshbadisa657@gmail.com
Project-URL: Bug Tracker, https://github.com/LokeshBadisa/txv/issues
Classifier: Programming Language :: Python :: 3
Classifier: License :: OSI Approved :: MIT License
Classifier: Operating System :: OS Independent
Requires-Python: >=3.8
License-File: LICENSE
Requires-Dist: einops
Requires-Dist: numpy
Requires-Dist: opencv-python
Requires-Dist: Pillow
Requires-Dist: Requests
Requires-Dist: torch
Requires-Dist: torchvision
Requires-Dist: tqdm
